aj090_hw_tools/__about__.py
aj090_hw_tools/__init__.py
aj090_hw_tools/__main__.py
aj090_hw_tools/common/__init__.py
aj090_hw_tools/common/const.py
aj090_hw_tools/targets/__init__.py
aj090_hw_tools/tools/__init__.py
aj090_hw_tools/tools/firmware.py
aj090_hw_tools/tools/info.py
aj090_hw_tools/tools/loadcell.py
aj090_hw_tools/tools/serial_number.py
aj090_hw_tools/tools/test.py
aj090_hw_tools-0.0.10.dist-info/METADATA
aj090_hw_tools-0.0.10.dist-info/WHEEL
aj090_hw_tools-0.0.10.dist-info/entry_points.txt
aj090_hw_tools-0.0.10.dist-info/licenses/LICENSE.txt
aj090_hw_tools-0.0.10.dist-info/RECORD
